odoo/addons/ebill_postfinance_customer_free_ref/README.rst
odoo/addons/ebill_postfinance_customer_free_ref/__init__.py
odoo/addons/ebill_postfinance_customer_free_ref/__manifest__.py
odoo/addons/ebill_postfinance_customer_free_ref/i18n/ebill_postfinance_customer_free_ref.pot
odoo/addons/ebill_postfinance_customer_free_ref/models/__init__.py
odoo/addons/ebill_postfinance_customer_free_ref/models/account_move.py
odoo/addons/ebill_postfinance_customer_free_ref/models/sale_order.py
odoo/addons/ebill_postfinance_customer_free_ref/readme/CONTRIBUTORS.md
odoo/addons/ebill_postfinance_customer_free_ref/readme/DESCRIPTION.md
odoo/addons/ebill_postfinance_customer_free_ref/static/description/icon.png
odoo/addons/ebill_postfinance_customer_free_ref/static/description/index.html
odoo/addons/ebill_postfinance_customer_free_ref/tests/__init__.py
odoo/addons/ebill_postfinance_customer_free_ref/tests/test_postfinance_customer_free_ref.py
odoo_addon_ebill_postfinance_customer_free_ref-18.0.1.0.0.2.dist-info/METADATA
odoo_addon_ebill_postfinance_customer_free_ref-18.0.1.0.0.2.dist-info/WHEEL
odoo_addon_ebill_postfinance_customer_free_ref-18.0.1.0.0.2.dist-info/top_level.txt
odoo_addon_ebill_postfinance_customer_free_ref-18.0.1.0.0.2.dist-info/RECORD
